telemetrx/TelemetrX.py
telemetrx/__init__.py
telemetrx-0.1.5.dist-info/LICENSE
telemetrx-0.1.5.dist-info/METADATA
telemetrx-0.1.5.dist-info/WHEEL
telemetrx-0.1.5.dist-info/top_level.txt
telemetrx-0.1.5.dist-info/RECORD
