Metadata-Version: 2.1
Name: telemetrx
Version: 0.1.5
Summary: a package for sending app telemetry data to the TelemetrX backend.
Classifier: Programming Language :: Python :: 3
Classifier: License :: Other/Proprietary License
Classifier: Operating System :: OS Independent
Requires-Python: >=3.10
License-File: LICENSE
Requires-Dist: aiohttp
Requires-Dist: python-dotenv
